iotitc/__init__.py
iotitc/bases_de_datos/__init__.py
iotitc/bases_de_datos/tools_influx.py
iotitc/raspberry/__init__.py
iotitc/raspberry/tools_raspberry.py
iotitc-1.0.1.dist-info/METADATA
iotitc-1.0.1.dist-info/WHEEL
iotitc-1.0.1.dist-info/RECORD
