Metadata-Version: 2.1
Name: iotitc
Version: 1.0.1
Summary: 
Author: CristianTacoronteRivero
Author-email: cristiantr.develop@gmail.com
Requires-Python: >=3.8,<4.0
Classifier: Programming Language :: Python :: 3
Classifier: Programming Language :: Python :: 3.8
Classifier: Programming Language :: Python :: 3.9
Classifier: Programming Language :: Python :: 3.10
Classifier: Programming Language :: Python :: 3.11
Requires-Dist: influxdb (>=5.3.1,<6.0.0)
Requires-Dist: pandas (>=1.5.2,<2.0.0)
Requires-Dist: psutil (>=5.9.4,<6.0.0)
